{"constitution_save":"8","reactions":[],"size":"huge","alignment":" нейтральний злий","damage_resistances":"","strength_save":"","skills":{"сприйняття":"3","атлетика":"9"},"slug":"frost_giant","hit_points":"138","charisma":"23","strength":"23","subtype":"","languages":"велетова","dexterity":"9","type":"Велет","actions":[{"name":"Мультиатака","desc":"Велет робить дві атаки дворучною сокирою."},{"desc":"_Атака зброєю ближнього бою:_ +9 до влучання, досяжність 10 ф, одна ціль. _Влучання:_ 25 (3к12 + 6) рубаних ушкоджень","name":"Дворучна сокира"},{"desc":"_Далекобійна атака зброєю:_ +9 до влучання, відстань 60\/240 ф, одна ціль. _Влучання:_ 28 (4к10 + 6) дробильних ушкоджень.","name":"Брила"}],"charisma_save":"4","legendary_actions":"","wisdom_save":"3","challenge_rating":"8","armor_desc":"клаптикова броня","condition_immunities":"","senses":"пасивна Увага 13","special_abilities":[],"armor_class":"15","legendary_desc":"","constitution":"21","speed":{},"damage_immunities":"холод","damage_vulnerabilities":"","hit_dice":"12к12 + 60","dexterity_save":"","wisdom":"10","name":"Морозний велет [Frost giant]","intelligence_save":"","intelligence":"9"}