{"type":"Звір","legendary_desc":"","intelligence":"2","armor_desc":"","dexterity_save":"","languages":"-","dexterity":"10","wisdom":"11","hit_points":"13","slug":"riding_horse","constitution":"12","wisdom_save":"","skills":{},"strength_save":"","damage_resistances":"","size":"large","senses":"пасивна Увага 10","hit_dice":"2к10 + 2","condition_immunities":"","strength":"16","damage_immunities":"","constitution_save":"","armor_class":"","subtype":"","challenge_rating":"1\/4","special_abilities":[],"damage_vulnerabilities":"","charisma_save":"","reactions":[],"speed":{},"legendary_actions":"","charisma":"16","alignment":" невизначений","name":"Їздовий кінь [Riding horse]","intelligence_save":"","actions":[{"desc":"_Атака зброєю ближнього бою:_ +5 до влучання, досяжність 5 ф, одна ціль. _Влучання:_ 8 (2к4 + 3) дробильних ушкоджень.","name":"Копита"}]}