{"senses":"темний зір 60 ф, пасивна Увага 8","special_abilities":[{"desc":"Якщо ушкодження зменшують пункти здоров'я зомбі до 0, він повинен зробити рятівний кидок Статури з КС 5 + отримані ушкодження, хіба що ушкодження від променистої енергії або від критичного влучання. У разі успіху пункти здоров'я зомбі натомість знижуються до 1.","name":"Стійкість невмерлих"}],"languages":"розуміє мови, які знав за життя, але не може говорити","slug":"zombie","alignment":" нейтральний злий","speed":{},"charisma":"13","strength_save":"","subtype":"","armor_class":"","hit_points":"22","dexterity_save":"","damage_immunities":"отрута","hit_dice":"3к8 + 9","damage_vulnerabilities":"","challenge_rating":"1\/4","intelligence_save":"","type":"Невмерлий","wisdom":"6","legendary_actions":"","reactions":[],"intelligence":"3","skills":{},"dexterity":"6","condition_immunities":"отруєний","name":"Зомбі [Zombie]","size":"medium","armor_desc":"","wisdom_save":"0","damage_resistances":"","charisma_save":"","actions":[{"name":"Стусан","desc":"_Атака зброєю ближнього бою:_ +3 до влучання, досяжність 5 ф, одна ціль. _Влучання:_ 4 (1к6 + 1) дробильних ушкоджень."}],"constitution_save":"","strength":"13","legendary_desc":"","constitution":"16"}